smart_status_bar/__init__.py
smart_status_bar/colors.py
smart_status_bar/status_bar.py
smart_status_bar-1.0.3.dist-info/LICENSE
smart_status_bar-1.0.3.dist-info/METADATA
smart_status_bar-1.0.3.dist-info/WHEEL
smart_status_bar-1.0.3.dist-info/top_level.txt
smart_status_bar-1.0.3.dist-info/RECORD
