Metadata-Version: 2.1
Name: smart-status-bar
Version: 1.0.3
Summary: A smart status bar for loops.
Home-page: https://github.com/Shreyansh7499/smart-status-bar
Author: Shreyansh Nagpal
Author-email: shreyanshnagpal7499@gmail.com
License: UNKNOWN
Platform: UNKNOWN
Classifier: Programming Language :: Python :: 3
Classifier: License :: OSI Approved :: MIT License
Classifier: Operating System :: OS Independent
Requires-Python: >=3.6
